{
    "classId": "idm.component.MeetingComponent.HeaderText",
    "comName": "标题文本",
    "className": "HeaderText",
    "comType": "common",
    "comLangue": "vue",
    "compositeAttr": [
        {
            "type": "colorPicker",
            "layoutType": "inline",
            "text": "背景颜色",
            "bindKey": "HeaderBgColor",
            "placeholder": "请选择颜色",
            "default": {
                "hex": "#FFFFFF",
                "hex8": "#FFFFFFFF"
            }
        },
        {
            "type": "input",
            "layoutType": "inline",
            "text": "唯一标识",
            "bindKey": "ctrlId",
            "disabled": true,
            "default": "@[packageid]",
            "desc": "",
            "helpUrl": ""
        },
        {
            "type": "group",
            "text": "文本基本属性",
            "desc": "提供设置组件能达到展示效果的基本属性设置信息",
            "children": [
                {
                    "type": "textarea",
                    "layoutType": "inline",
                    "text": "文本内容",
                    "bindKey": "fontContent",
                    "default": "文本内容"
                },
                {
                    "type": "switch",
                    "layoutType": "inline",
                    "text": "title",
                    "bindKey": "htmlTitle",
                    "desc": "将内容显示为html标签的title，也就是鼠标放上去会有显示文本内容的文字",
                    "disabled": false
                },
                {
                    "type": "radio",
                    "layoutType": "inline",
                    "text": "默认状态",
                    "bindKey": "defaultStatus",
                    "dictionary": [
                        {
                            "label": "普通",
                            "value": "default"
                        },
                        {
                            "label": "隐藏",
                            "value": "hidden"
                        }
                    ],
                    "default": "default"
                }
            ]
        },
        {
            "type": "group",
            "text": "样式设置",
            "desc": "点击？查看样式设置用法指南",
            "helpUrl": "",
            "children": [
                {
                    "type": "box",
                    "layoutType": "block",
                    "text": "内外边距",
                    "bindKey": "box"
                },
                {
                    "type": "inlineGroup",
                    "text": "宽高",
                    "children": [
                        {
                            "type": "input",
                            "layoutType": "block",
                            "text": "宽",
                            "desc": "填写auto则为自适应，或者使用px、%、vw等单位，比如100%、100px、100vw等等",
                            "bindKey": "width",
                            "width": "60px",
                            "default": "auto"
                        },
                        {
                            "type": "input",
                            "layoutType": "block",
                            "text": "高",
                            "desc": "填写auto则为自适应，或者使用px、%、vh等单位，比如100%、100px、100vh等等",
                            "bindKey": "height",
                            "width": "60px",
                            "default": "auto"
                        }
                    ]
                },
                {
                    "type": "group",
                    "text": "背景设置",
                    "desc": "点击？查看背景设置用法指南",
                    "helpUrl": "",
                    "children": [
                        {
                            "type": "colorPicker",
                            "layoutType": "inline",
                            "text": "背景色",
                            "bindKey": "bgColor",
                            "placeholder": "请选择颜色",
                            "default": {}
                        },
                        {
                            "type": "uploadImage",
                            "layoutType": "inline",
                            "text": "背景图片",
                            "bindKey": "bgImgUrl",
                            "placeholder": "可输入图片地址或直接上传"
                        },
                        {
                            "type": "inputNumberUnit",
                            "layoutType": "inline",
                            "text": "横向偏移",
                            "bindKey": "positionX",
                            "dictionary": [
                                {
                                    "label": "px",
                                    "value": "px"
                                },
                                {
                                    "label": "%",
                                    "value": "%"
                                },
                                {
                                    "label": "em",
                                    "value": "em"
                                }
                            ],
                            "display": "@[bgImgUrl]"
                        },
                        {
                            "type": "inputNumberUnit",
                            "layoutType": "inline",
                            "text": "纵向偏移",
                            "bindKey": "positionY",
                            "dictionary": [
                                {
                                    "label": "px",
                                    "value": "px"
                                },
                                {
                                    "label": "%",
                                    "value": "%"
                                },
                                {
                                    "label": "em",
                                    "value": "em"
                                }
                            ],
                            "display": "@[bgImgUrl]"
                        },
                        {
                            "type": "radio",
                            "layoutType": "block",
                            "text": "背景大小",
                            "bindKey": "bgSize",
                            "dictionary": [
                                {
                                    "label": "裁切显示",
                                    "value": "cover"
                                },
                                {
                                    "label": "完全显示",
                                    "value": "contain"
                                },
                                {
                                    "label": "自定义",
                                    "value": "custom"
                                }
                            ],
                            "display": "@[bgImgUrl]"
                        },
                        {
                            "type": "inputNumberUnit",
                            "layoutType": "inline",
                            "text": "宽度",
                            "bindKey": "bgSizeWidth",
                            "dictionary": [
                                {
                                    "label": "px",
                                    "value": "px"
                                },
                                {
                                    "label": "%",
                                    "value": "%"
                                },
                                {
                                    "label": "em",
                                    "value": "em"
                                }
                            ],
                            "display": "@[bgSize=='custom']"
                        },
                        {
                            "type": "inputNumberUnit",
                            "layoutType": "inline",
                            "text": "高度",
                            "bindKey": "bgSizeHeight",
                            "dictionary": [
                                {
                                    "label": "px",
                                    "value": "px"
                                },
                                {
                                    "label": "%",
                                    "value": "%"
                                },
                                {
                                    "label": "em",
                                    "value": "em"
                                }
                            ],
                            "display": "@[bgSize=='custom']"
                        },
                        {
                            "type": "radio",
                            "layoutType": "block",
                            "text": "平铺模式",
                            "bindKey": "bgRepeat",
                            "dictionary": [
                                {
                                    "label": "双向重复",
                                    "value": "repeat"
                                },
                                {
                                    "label": "水平重复",
                                    "value": "repeat-x"
                                },
                                {
                                    "label": "垂直重复",
                                    "value": "repeat-y"
                                },
                                {
                                    "label": "不重复",
                                    "value": "no-repeat"
                                },
                                {
                                    "label": "继承",
                                    "value": "inherit"
                                }
                            ],
                            "display": "@[bgImgUrl]"
                        },
                        {
                            "type": "radio",
                            "layoutType": "inline",
                            "text": "背景模式",
                            "bindKey": "bgAttachment",
                            "dictionary": [
                                {
                                    "label": "固定",
                                    "value": "fixed"
                                },
                                {
                                    "label": "滚动",
                                    "value": "scroll"
                                },
                                {
                                    "label": "继承",
                                    "value": "inherit"
                                }
                            ],
                            "display": "@[bgImgUrl]"
                        }
                    ]
                },
                {
                    "type": "border",
                    "layoutType": "block",
                    "text": "边框",
                    "bindKey": "border"
                },
                {
                    "type": "font",
                    "layoutType": "block",
                    "text": "文字",
                    "bindKey": "font",
                    "default":{
                        "fontFamily": "impact, 'microsoft yahei'",
                        "fontColors": {
                            "hex": "#000000",
                            "hex8": "#000000FF"
                        },
                        "fontWeight": "600 Semi Bold",
                        "fontStyle": "normal",
                        "fontSize": 21,
                        "fontSizeUnit": "px",
                        "fontLineHeight": 21,
                        "fontLineHeightUnit": "px",
                        "fontTextAlign": "center",
                        "fontLetterSpacing": 6,
                        "fontLetterSpacingUnit": "px"
                    }
                }
            ]
        },
        {
            "type": "group",
            "text": "高级",
            "desc": "点击？查看高级设置用法指南",
            "children": [
                {
                    "type": "actionSelect",
                    "layoutType": "block",
                    "text": "点击时动作",
                    "bindKey": "clickFunction",
                    "desc": "点击的时候会调用设置的自定义函数，接收参数为格式为{...自定义的}",
                    "multiple": true
                },
                {
                    "type": "select",
                    "layoutType": "inline",
                    "text": "动态内容",
                    "bindKey": "dataSourceType",
                    "desc": "通过这些方式去动态获取结果值显示成文本内容",
                    "dictionary": [
                        {
                            "label": "自定义接口",
                            "value": "customInterface"
                        },
                        {
                            "label": "页面统一接口",
                            "value": "pageCommonInterface"
                        },
                        {
                            "label": "自定义函数",
                            "value": "customFunction"
                        },
                        {
                            "label": "接收联动消息",
                            "value": "receiveMessage"
                        }
                    ],
                    "default": "customInterface"
                },
                {
                    "type": "input",
                    "layoutType": "inline",
                    "text": "接口地址",
                    "bindKey": "customInterfaceUrl",
                    "desc": "用于获取数据源的接口地址，请按照统一标准的返回格式返回文本数据，格式如下：{\"code\":\"200\",\"data\":\"\",...}",
                    "display": "@[dataSourceType=='customInterface']"
                },
                {
                    "type": "input",
                    "layoutType": "inline",
                    "text": "结果集名",
                    "bindKey": "dataName",
                    "desc": "页面接口设定的结果集名称，位置为：页面设置》高级设置》页面接口",
                    "default": "",
                    "placeholder": "示例：resultData",
                    "display": "@[dataSourceType=='pageCommonInterface']"
                },
                {
                    "type": "textarea",
                    "layoutType": "inline",
                    "text": "显示字段",
                    "bindKey": "dataFiled",
                    "desc": "根据接口返回数据格式指定结果集的字段，比如结果集名为resultData（自定义接口忽略）且它的值为{data:{filedName:[{\"text\":\"\",\"value\":\"\",\"check\":true}]}}，则这里应该填写data.filedName",
                    "default": "",
                    "placeholder": "示例：data.filedName 或者 [0].data[0].filedName",
                    "display": "@[dataSourceType!='customFunction'&&dataSourceType!='receiveMessage']"
                },
                {
                    "type": "actionSelect",
                    "layoutType": "block",
                    "text": "自定义函数",
                    "bindKey": "customFunction",
                    "desc": "获取动态文本内容、自定义接口回调、页面统一接口回调的时候会调用此方法，返回数据格式为字符串，接收参数：{...自定义,interfaceData:自定义接口或页面统一接口的返回结果,expressData:表达式替换后的结果,moduleObject:组件对象,receiveData:接收到的消息数据}",
                    "multiple": false
                }
            ]
        },
    










        {
            "type": "group",
            "text": "左侧按钮基本属性",
            "desc": "提供设置组件能达到展示效果的基本属性设置信息",
            "children": [
                {
                    "type": "input",
                    "layoutType": "inline",
                    "text": "标题",
                    "bindKey": "Btn1label",
                    "default": ""
                },
                {
                    "type": "radio",
                    "layoutType": "inline",
                    "text": "尺寸",
                    "bindKey": "Btn1size",
                    "dictionary": [
                        {
                            "label": "小",
                            "value": "small"
                        },
                        {
                            "label": "中",
                            "value": "default"
                        },
                        {
                            "label": "大",
                            "value": "large"
                        }
                    ],
                    "default": "default"
                },
                {
                    "type": "radio",
                    "layoutType": "inline",
                    "text": "默认状态",
                    "bindKey": "Btn1defaultStatus",
                    "dictionary": [
                        {
                            "label": "普通",
                            "value": "default"
                        },
                        {
                            "label": "禁用",
                            "value": "disabled"
                        },
                        {
                            "label": "隐藏",
                            "value": "hidden"
                        }
                    ],
                    "default": "default"
                },
                {
                    "type": "iconSelect",
                    "layoutType": "inline",
                    "text": "图标",
                    "bindKey": "Btn1icon",
                    "placeholder": "请选择",
                    "default":["idm-icon-arrowleft"]
                },
                {
                    "type": "inputNumberUnit",
                    "layoutType": "inline",
                    "text": "图标大小",
                    "bindKey": "Btn1iconBox",
                    "placeholder": "图标大小",
                    "dictionary": [
                        {
                            "label": "px",
                            "value": "px"
                        },
                        {
                            "label": "em",
                            "value": "em"
                        },
                        {
                            "label": "%",
                            "value": "%"
                        }
                    ],
                    "default":
                    {
                        "inputVal": 21,
                        "selectVal": "px"
                    }
                },
                {
                    "type": "colorPicker",
                    "layoutType": "inline",
                    "text": "图标颜色",
                    "bindKey": "Btn1iconColor",
                    "placeholder": "请选择颜色",
                    "default": {
                        "hex": "#000000",
                        "hex8": "#000000FF"
                    }
                },
                {
                    "type": "radio",
                    "layoutType": "inline",
                    "text": "按钮类型",
                    "bindKey": "Btn1buttonType",
                    "dictionary": [
                        {
                            "label": "主要",
                            "value": "primary"
                        },
                        {
                            "label": "次要",
                            "value": "default"
                        },
                        {
                            "label": "虚线",
                            "value": "dashed"
                        },
                        {
                            "label": "危险",
                            "value": "danger"
                        },
                        {
                            "label": "链接",
                            "value": "link"
                        },
                        {
                            "label": "自定义",
                            "value": "customBtn1"
                        }
                    ],
                    "default": "link"
                },
                {
                    "type": "switch",
                    "layoutType": "inline",
                    "text": "加载状态",
                    "desc":"开启将启用点击出现loading状态，需要在自定义方法中关闭才行（ctx._this.isLoading=false）",
                    "bindKey": "Btn1openLoading"
                },
                {
                    "type": "font",
                    "layoutType": "block",
                    "text": "文字",
                    "bindKey": "Btn1font"
                }
            ]
        },
        {
            "type": "group",
            "text": "样式设置(基础)",
            "desc": "点击？查看样式设置用法指南",
            "helpUrl": "",
            "children": [
                {
                    "type": "box",
                    "layoutType": "block",
                    "text": "内外边距",
                    "bindKey": "Btn1box"
                },
                {
                    "type": "inlineGroup",
                    "text": "宽高",
                    "children": [
                        {
                            "type": "input",
                            "layoutType": "block",
                            "text": "宽",
                            "desc": "填写auto则为自适应，或者使用px、%、vw等单位，比如100%、100px、100vw等等",
                            "bindKey": "Btn1width",
                            "width": "60px",
                            "default": "auto"
                        },
                        {
                            "type": "input",
                            "layoutType": "block",
                            "text": "高",
                            "desc": "填写auto则为默认大小，或者使用px、%、vh等单位，比如100%、100px、100vh等等",
                            "bindKey": "Btn1height",
                            "width": "60px",
                            "default": "auto"
                        }
                    ]
                }
            ]
        },
        {
            "type": "group",
            "text": "样式设置(默认)",
            "desc": "点击？查看样式设置用法指南",
            "helpUrl": "",
            "display": "@[Btn1buttonType=='customBtn1']",
            "children": [
                {
                    "type": "font",
                    "layoutType": "block",
                    "text": "文字",
                    "bindKey": "Btn1fontDefault"
                },
                {
                    "type": "border",
                    "layoutType": "block",
                    "text": "边框设置",
                    "bindKey": "Btn1borderDefault"
                },
                {
                    "type": "colorPicker",
                    "layoutType": "inline",
                    "text": "背景色",
                    "bindKey": "Btn1bgColorDefault",
                    "placeholder": "请选择颜色",
                    "default": {}
                },
                {
                    "type": "uploadImage",
                    "layoutType": "inline",
                    "text": "背景图片",
                    "bindKey": "Btn1bgImgUrlDefault",
                    "placeholder": "可输入图片地址或直接上传"
                },
                {
                    "type": "inputNumberUnit",
                    "layoutType": "inline",
                    "text": "横向偏移",
                    "bindKey": "Btn1positionXDefault",
                    "dictionary": [
                        {
                            "label": "px",
                            "value": "px"
                        },
                        {
                            "label": "%",
                            "value": "%"
                        },
                        {
                            "label": "em",
                            "value": "em"
                        }
                    ],
                    "display": "@[Btn1bgImgUrlDefault]"
                },
                {
                    "type": "inputNumberUnit",
                    "layoutType": "inline",
                    "text": "纵向偏移",
                    "bindKey": "Btn1positionYDefault",
                    "dictionary": [
                        {
                            "label": "px",
                            "value": "px"
                        },
                        {
                            "label": "%",
                            "value": "%"
                        },
                        {
                            "label": "em",
                            "value": "em"
                        }
                    ],
                    "display": "@[Btn1bgImgUrlDefault]"
                },
                {
                    "type": "radio",
                    "layoutType": "block",
                    "text": "背景大小",
                    "bindKey": "Btn1bgSizeDefault",
                    "dictionary": [
                        {
                            "label": "裁切显示",
                            "value": "cover"
                        },
                        {
                            "label": "完全显示",
                            "value": "contain"
                        },
                        {
                            "label": "自定义",
                            "value": "customBtn1"
                        }
                    ],
                    "display": "@[Btn1bgImgUrlDefault]"
                },
                {
                    "type": "inputNumberUnit",
                    "layoutType": "inline",
                    "text": "宽度",
                    "bindKey": "Btn1bgSizeWidthDefault",
                    "dictionary": [
                        {
                            "label": "px",
                            "value": "px"
                        },
                        {
                            "label": "%",
                            "value": "%"
                        },
                        {
                            "label": "em",
                            "value": "em"
                        }
                    ],
                    "display": "@[bgSizeDefault=='customBtn1']"
                },
                {
                    "type": "inputNumberUnit",
                    "layoutType": "inline",
                    "text": "高度",
                    "bindKey": "Btn1bgSizeHeightDefault",
                    "dictionary": [
                        {
                            "label": "px",
                            "value": "px"
                        },
                        {
                            "label": "%",
                            "value": "%"
                        },
                        {
                            "label": "em",
                            "value": "em"
                        }
                    ],
                    "display": "@[bgSizeDefault=='customBtn1']"
                },
                {
                    "type": "radio",
                    "layoutType": "block",
                    "text": "平铺模式",
                    "bindKey": "Btn1bgRepeatDefault",
                    "dictionary": [
                        {
                            "label": "双向重复",
                            "value": "repeat"
                        },
                        {
                            "label": "水平重复",
                            "value": "repeat-x"
                        },
                        {
                            "label": "垂直重复",
                            "value": "repeat-y"
                        },
                        {
                            "label": "不重复",
                            "value": "no-repeat"
                        },
                        {
                            "label": "继承",
                            "value": "inherit"
                        }
                    ],
                    "display": "@[Btn1bgImgUrlDefault]"
                },
                {
                    "type": "radio",
                    "layoutType": "inline",
                    "text": "背景模式",
                    "bindKey": "Btn1bgAttachmentDefault",
                    "dictionary": [
                        {
                            "label": "固定",
                            "value": "fixed"
                        },
                        {
                            "label": "滚动",
                            "value": "scroll"
                        },
                        {
                            "label": "继承",
                            "value": "inherit"
                        }
                    ],
                    "display": "@[Btn1bgImgUrlDefault]"
                }
            ]
        },
        {
            "type": "group",
            "text": "样式设置(hover)",
            "desc": "点击？查看样式设置用法指南",
            "helpUrl": "",
            "display": "@[Btn1buttonType=='customBtn1']",
            "children": [
                {
                    "type": "font",
                    "layoutType": "block",
                    "text": "文字",
                    "bindKey": "Btn1fontHover"
                },
                {
                    "type": "border",
                    "layoutType": "block",
                    "text": "边框设置",
                    "bindKey": "Btn1borderHover"
                },
                {
                    "type": "colorPicker",
                    "layoutType": "inline",
                    "text": "背景色",
                    "bindKey": "Btn1bgColorHover",
                    "placeholder": "请选择颜色",
                    "default": {}
                },
                {
                    "type": "uploadImage",
                    "layoutType": "inline",
                    "text": "背景图片",
                    "bindKey": "Btn1bgImgUrlHover",
                    "placeholder": "可输入图片地址或直接上传"
                },
                {
                    "type": "inputNumberUnit",
                    "layoutType": "inline",
                    "text": "横向偏移",
                    "bindKey": "Btn1positionXHover",
                    "dictionary": [
                        {
                            "label": "px",
                            "value": "px"
                        },
                        {
                            "label": "%",
                            "value": "%"
                        },
                        {
                            "label": "em",
                            "value": "em"
                        }
                    ],
                    "display": "@[bgImgUrlHover]"
                },
                {
                    "type": "inputNumberUnit",
                    "layoutType": "inline",
                    "text": "纵向偏移",
                    "bindKey": "Btn1positionYHover",
                    "dictionary": [
                        {
                            "label": "px",
                            "value": "px"
                        },
                        {
                            "label": "%",
                            "value": "%"
                        },
                        {
                            "label": "em",
                            "value": "em"
                        }
                    ],
                    "display": "@[bgImgUrlHover]"
                },
                {
                    "type": "radio",
                    "layoutType": "block",
                    "text": "背景大小",
                    "bindKey": "Btn1bgSizeHover",
                    "dictionary": [
                        {
                            "label": "裁切显示",
                            "value": "cover"
                        },
                        {
                            "label": "完全显示",
                            "value": "contain"
                        },
                        {
                            "label": "自定义",
                            "value": "customBtn1"
                        }
                    ],
                    "display": "@[bgImgUrlHover]"
                },
                {
                    "type": "inputNumberUnit",
                    "layoutType": "inline",
                    "text": "宽度",
                    "bindKey": "Btn1bgSizeWidthHover",
                    "dictionary": [
                        {
                            "label": "px",
                            "value": "px"
                        },
                        {
                            "label": "%",
                            "value": "%"
                        },
                        {
                            "label": "em",
                            "value": "em"
                        }
                    ],
                    "display": "@[bgSizeHover=='customBtn1']"
                },
                {
                    "type": "inputNumberUnit",
                    "layoutType": "inline",
                    "text": "高度",
                    "bindKey": "Btn1bgSizeHeightHover",
                    "dictionary": [
                        {
                            "label": "px",
                            "value": "px"
                        },
                        {
                            "label": "%",
                            "value": "%"
                        },
                        {
                            "label": "em",
                            "value": "em"
                        }
                    ],
                    "display": "@[bgSizeHover=='customBtn1']"
                },
                {
                    "type": "radio",
                    "layoutType": "block",
                    "text": "平铺模式",
                    "bindKey": "Btn1bgRepeatHover",
                    "dictionary": [
                        {
                            "label": "双向重复",
                            "value": "repeat"
                        },
                        {
                            "label": "水平重复",
                            "value": "repeat-x"
                        },
                        {
                            "label": "垂直重复",
                            "value": "repeat-y"
                        },
                        {
                            "label": "不重复",
                            "value": "no-repeat"
                        },
                        {
                            "label": "继承",
                            "value": "inherit"
                        }
                    ],
                    "display": "@[bgImgUrlHover]"
                },
                {
                    "type": "radio",
                    "layoutType": "inline",
                    "text": "背景模式",
                    "bindKey": "Btn1bgAttachmentHover",
                    "dictionary": [
                        {
                            "label": "固定",
                            "value": "fixed"
                        },
                        {
                            "label": "滚动",
                            "value": "scroll"
                        },
                        {
                            "label": "继承",
                            "value": "inherit"
                        }
                    ],
                    "display": "@[bgImgUrlHover]"
                }
            ]
        },
        {
            "type": "group",
            "text": "样式设置(focus)",
            "desc": "点击？查看样式设置用法指南",
            "helpUrl": "",
            "display": "@[Btn1buttonType=='customBtn1']",
            "children": [
                {
                    "type": "font",
                    "layoutType": "block",
                    "text": "文字",
                    "bindKey": "Btn1fontFocus"
                },
                {
                    "type": "border",
                    "layoutType": "block",
                    "text": "边框设置",
                    "bindKey": "Btn1borderFocus"
                },
                {
                    "type": "colorPicker",
                    "layoutType": "inline",
                    "text": "背景色",
                    "bindKey": "Btn1bgColorFocus",
                    "placeholder": "请选择颜色",
                    "default": {}
                },
                {
                    "type": "uploadImage",
                    "layoutType": "inline",
                    "text": "背景图片",
                    "bindKey": "Btn1bgImgUrlFocus",
                    "placeholder": "可输入图片地址或直接上传"
                },
                {
                    "type": "inputNumberUnit",
                    "layoutType": "inline",
                    "text": "横向偏移",
                    "bindKey": "Btn1positionXFocus",
                    "dictionary": [
                        {
                            "label": "px",
                            "value": "px"
                        },
                        {
                            "label": "%",
                            "value": "%"
                        },
                        {
                            "label": "em",
                            "value": "em"
                        }
                    ],
                    "display": "@[bgImgUrlFocus]"
                },
                {
                    "type": "inputNumberUnit",
                    "layoutType": "inline",
                    "text": "纵向偏移",
                    "bindKey": "Btn1positionYFocus",
                    "dictionary": [
                        {
                            "label": "px",
                            "value": "px"
                        },
                        {
                            "label": "%",
                            "value": "%"
                        },
                        {
                            "label": "em",
                            "value": "em"
                        }
                    ],
                    "display": "@[bgImgUrlFocus]"
                },
                {
                    "type": "radio",
                    "layoutType": "block",
                    "text": "背景大小",
                    "bindKey": "Btn1bgSizeFocus",
                    "dictionary": [
                        {
                            "label": "裁切显示",
                            "value": "cover"
                        },
                        {
                            "label": "完全显示",
                            "value": "contain"
                        },
                        {
                            "label": "自定义",
                            "value": "customBtn1"
                        }
                    ],
                    "display": "@[bgImgUrlFocus]"
                },
                {
                    "type": "inputNumberUnit",
                    "layoutType": "inline",
                    "text": "宽度",
                    "bindKey": "Btn1bgSizeWidthFocus",
                    "dictionary": [
                        {
                            "label": "px",
                            "value": "px"
                        },
                        {
                            "label": "%",
                            "value": "%"
                        },
                        {
                            "label": "em",
                            "value": "em"
                        }
                    ],
                    "display": "@[bgSizeFocus=='customBtn1']"
                },
                {
                    "type": "inputNumberUnit",
                    "layoutType": "inline",
                    "text": "高度",
                    "bindKey": "Btn1bgSizeHeightFocus",
                    "dictionary": [
                        {
                            "label": "px",
                            "value": "px"
                        },
                        {
                            "label": "%",
                            "value": "%"
                        },
                        {
                            "label": "em",
                            "value": "em"
                        }
                    ],
                    "display": "@[bgSizeFocus=='customBtn1']"
                },
                {
                    "type": "radio",
                    "layoutType": "block",
                    "text": "平铺模式",
                    "bindKey": "Btn1bgRepeatFocus",
                    "dictionary": [
                        {
                            "label": "双向重复",
                            "value": "repeat"
                        },
                        {
                            "label": "水平重复",
                            "value": "repeat-x"
                        },
                        {
                            "label": "垂直重复",
                            "value": "repeat-y"
                        },
                        {
                            "label": "不重复",
                            "value": "no-repeat"
                        },
                        {
                            "label": "继承",
                            "value": "inherit"
                        }
                    ],
                    "display": "@[bgImgUrlFocus]"
                },
                {
                    "type": "radio",
                    "layoutType": "inline",
                    "text": "背景模式",
                    "bindKey": "Btn1bgAttachmentFocus",
                    "dictionary": [
                        {
                            "label": "固定",
                            "value": "fixed"
                        },
                        {
                            "label": "滚动",
                            "value": "scroll"
                        },
                        {
                            "label": "继承",
                            "value": "inherit"
                        }
                    ],
                    "display": "@[bgImgUrlFocus]"
                }
            ]
        },
        {
            "type": "group",
            "text": "样式设置(active)",
            "desc": "点击？查看样式设置用法指南",
            "helpUrl": "",
            "display": "@[Btn1buttonType=='customBtn1']",
            "children": [
                {
                    "type": "font",
                    "layoutType": "block",
                    "text": "文字",
                    "bindKey": "Btn1fontActive"
                },
                {
                    "type": "border",
                    "layoutType": "block",
                    "text": "边框设置",
                    "bindKey": "Btn1borderActive"
                },
                {
                    "type": "colorPicker",
                    "layoutType": "inline",
                    "text": "背景色",
                    "bindKey": "Btn1bgColorActive",
                    "placeholder": "请选择颜色",
                    "default": {}
                },
                {
                    "type": "uploadImage",
                    "layoutType": "inline",
                    "text": "背景图片",
                    "bindKey": "Btn1bgImgUrlActive",
                    "placeholder": "可输入图片地址或直接上传"
                },
                {
                    "type": "inputNumberUnit",
                    "layoutType": "inline",
                    "text": "横向偏移",
                    "bindKey": "Btn1positionXActive",
                    "dictionary": [
                        {
                            "label": "px",
                            "value": "px"
                        },
                        {
                            "label": "%",
                            "value": "%"
                        },
                        {
                            "label": "em",
                            "value": "em"
                        }
                    ],
                    "display": "@[bgImgUrlActive]"
                },
                {
                    "type": "inputNumberUnit",
                    "layoutType": "inline",
                    "text": "纵向偏移",
                    "bindKey": "Btn1positionYActive",
                    "dictionary": [
                        {
                            "label": "px",
                            "value": "px"
                        },
                        {
                            "label": "%",
                            "value": "%"
                        },
                        {
                            "label": "em",
                            "value": "em"
                        }
                    ],
                    "display": "@[bgImgUrlActive]"
                },
                {
                    "type": "radio",
                    "layoutType": "block",
                    "text": "背景大小",
                    "bindKey": "Btn1bgSizeActive",
                    "dictionary": [
                        {
                            "label": "裁切显示",
                            "value": "cover"
                        },
                        {
                            "label": "完全显示",
                            "value": "contain"
                        },
                        {
                            "label": "自定义",
                            "value": "customBtn1"
                        }
                    ],
                    "display": "@[bgImgUrlActive]"
                },
                {
                    "type": "inputNumberUnit",
                    "layoutType": "inline",
                    "text": "宽度",
                    "bindKey": "Btn1bgSizeWidthActive",
                    "dictionary": [
                        {
                            "label": "px",
                            "value": "px"
                        },
                        {
                            "label": "%",
                            "value": "%"
                        },
                        {
                            "label": "em",
                            "value": "em"
                        }
                    ],
                    "display": "@[bgSizeActive=='customBtn1']"
                },
                {
                    "type": "inputNumberUnit",
                    "layoutType": "inline",
                    "text": "高度",
                    "bindKey": "Btn1bgSizeHeightActive",
                    "dictionary": [
                        {
                            "label": "px",
                            "value": "px"
                        },
                        {
                            "label": "%",
                            "value": "%"
                        },
                        {
                            "label": "em",
                            "value": "em"
                        }
                    ],
                    "display": "@[bgSizeActive=='customBtn1']"
                },
                {
                    "type": "radio",
                    "layoutType": "block",
                    "text": "平铺模式",
                    "bindKey": "Btn1bgRepeatActive",
                    "dictionary": [
                        {
                            "label": "双向重复",
                            "value": "repeat"
                        },
                        {
                            "label": "水平重复",
                            "value": "repeat-x"
                        },
                        {
                            "label": "垂直重复",
                            "value": "repeat-y"
                        },
                        {
                            "label": "不重复",
                            "value": "no-repeat"
                        },
                        {
                            "label": "继承",
                            "value": "inherit"
                        }
                    ],
                    "display": "@[bgImgUrlActive]"
                },
                {
                    "type": "radio",
                    "layoutType": "inline",
                    "text": "背景模式",
                    "bindKey": "Btn1bgAttachmentActive",
                    "dictionary": [
                        {
                            "label": "固定",
                            "value": "fixed"
                        },
                        {
                            "label": "滚动",
                            "value": "scroll"
                        },
                        {
                            "label": "继承",
                            "value": "inherit"
                        }
                    ],
                    "display": "@[bgImgUrlActive]"
                }
            ]
        },
        {
            "type": "group",
            "text": "高级",
            "desc": "点击？查看高级设置用法指南",
            "children": [
                {
                    "type": "actionSelect",
                    "layoutType": "block",
                    "text": "点击时动作",
                    "bindKey": "Btn1clickFunction",
                    "desc": "点击的时候会调用设置的自定义函数，接收参数为格式为{customBtn1Param:自定义的}",
                    "multiple": true
                },
                {
                    "type": "pageModuleSelect",
                    "layoutType": "block",
                    "text": "点击发送组件消息范围",
                    "desc": "当点击的时候需要联动其他组件结果值的组件范围",
                    "bindKey": "Btn1linkagePageModule",
                    "multiple": true
                },
                {
                    "type": "input",
                    "layoutType": "inline",
                    "text": "消息Key",
                    "bindKey": "Btn1messageKey",
                    "desc": "发送组件消息的messageKey，用于联合匹配其他组件进行判定",
                    "default": "buttonClick"
                }
            ]
        },

        {
            "type": "group",
            "text": "右侧按钮基本属性",
            "desc": "提供设置组件能达到展示效果的基本属性设置信息",
            "children": [
                {
                    "type": "input",
                    "layoutType": "inline",
                    "text": "标题",
                    "bindKey": "Btn2label",
                    "default": "更多"
                },
                {
                    "type": "radio",
                    "layoutType": "inline",
                    "text": "尺寸",
                    "bindKey": "Btn2size",
                    "dictionary": [
                        {
                            "label": "小",
                            "value": "small"
                        },
                        {
                            "label": "中",
                            "value": "default"
                        },
                        {
                            "label": "大",
                            "value": "large"
                        }
                    ],
                    "default": "default"
                },
                {
                    "type": "radio",
                    "layoutType": "inline",
                    "text": "默认状态",
                    "bindKey": "Btn2defaultStatus",
                    "dictionary": [
                        {
                            "label": "普通",
                            "value": "default"
                        },
                        {
                            "label": "禁用",
                            "value": "disabled"
                        },
                        {
                            "label": "隐藏",
                            "value": "hidden"
                        }
                    ],
                    "default": "default"
                },
                {
                    "type": "iconSelect",
                    "layoutType": "inline",
                    "text": "图标",
                    "bindKey": "Btn2icon",
                    "placeholder": "请选择",
                    "default":["idm-icon-arrowright"]
                },
                {
                    "type": "inputNumberUnit",
                    "layoutType": "inline",
                    "text": "图标大小",
                    "bindKey": "Btn2iconBox",
                    "placeholder": "图标大小",
                    "dictionary": [
                        {
                            "label": "px",
                            "value": "px"
                        },
                        {
                            "label": "em",
                            "value": "em"
                        },
                        {
                            "label": "%",
                            "value": "%"
                        }
                    ],
                    "default":
                    {
                        "inputVal": 21,
                        "selectVal": "px"
                    }
                },
                {
                    "type": "colorPicker",
                    "layoutType": "inline",
                    "text": "图标颜色",
                    "bindKey": "Btn2iconColor",
                    "placeholder": "请选择颜色",
                    "default": {
                        "hex": "#000000",
                        "hex8": "#000000FF"
                    }
                },
                {
                    "type": "radio",
                    "layoutType": "inline",
                    "text": "按钮类型",
                    "bindKey": "Btn2buttonType",
                    "dictionary": [
                        {
                            "label": "主要",
                            "value": "primary"
                        },
                        {
                            "label": "次要",
                            "value": "default"
                        },
                        {
                            "label": "虚线",
                            "value": "dashed"
                        },
                        {
                            "label": "危险",
                            "value": "danger"
                        },
                        {
                            "label": "链接",
                            "value": "link"
                        },
                        {
                            "label": "自定义",
                            "value": "customBtn2"
                        }
                    ],
                    "default": "link"
                },
                {
                    "type": "switch",
                    "layoutType": "inline",
                    "text": "加载状态",
                    "desc":"开启将启用点击出现loading状态，需要在自定义方法中关闭才行（ctx._this.isLoading=false）",
                    "bindKey": "Btn2openLoading"
                }
            ]
        },
        {
            "type": "group",
            "text":"文字基本属性",
            "desc":"控制按钮内文字格式",
            "children": [
                {
                    "type": "font",
                    "layoutType": "block",
                    "text": "文字",
                    "bindKey": "Btn2font",
                    "default":{
                        "fontFamily": "impact, 'microsoft yahei'",
                        "fontColors": {
                            "hex": "##727272",
                            "hex8": "##727272FF"
                        },
                        "fontWeight": "600 Semi Bold",
                        "fontStyle": "normal",
                        "fontSize": 14,
                        "fontSizeUnit": "px",
                        "fontLineHeight": 14,
                        "fontLineHeightUnit": "px"
                    }
                },
                {
                    "type": "box",
                    "layoutType": "block",
                    "text": "内外边距",
                    "bindKey": "Btn2TextBox",
                    "default":{
                        "marginTopVal": "0px",
                        "marginRightVal": "0px",
                        "marginBottomVal": "0px",
                        "marginLeftVal": "0px",
                        "paddingTopVal": "0px",
                        "paddingRightVal": "10px",
                        "paddingBottomVal": "0px",
                        "paddingLeftVal": "0px"
                    }
                }
            ]
        },
        {
            "type": "group",
            "text": "样式设置(基础)",
            "desc": "点击？查看样式设置用法指南",
            "helpUrl": "",
            "children": [
                {
                    "type": "box",
                    "layoutType": "block",
                    "text": "内外边距",
                    "bindKey": "Btn2box"
                },
                {
                    "type": "inlineGroup",
                    "text": "宽高",
                    "children": [
                        {
                            "type": "input",
                            "layoutType": "block",
                            "text": "宽",
                            "desc": "填写auto则为自适应，或者使用px、%、vw等单位，比如100%、100px、100vw等等",
                            "bindKey": "Btn2width",
                            "width": "60px",
                            "default": "auto"
                        },
                        {
                            "type": "input",
                            "layoutType": "block",
                            "text": "高",
                            "desc": "填写auto则为默认大小，或者使用px、%、vh等单位，比如100%、100px、100vh等等",
                            "bindKey": "Btn2height",
                            "width": "60px",
                            "default": "auto"
                        }
                    ]
                }
            ]
        },
        {
            "type": "group",
            "text": "样式设置(默认)",
            "desc": "点击？查看样式设置用法指南",
            "helpUrl": "",
            "display": "@[Btn2buttonType=='customBtn2']",
            "children": [
                {
                    "type": "font",
                    "layoutType": "block",
                    "text": "文字",
                    "bindKey": "Btn2fontDefault"
                },
                {
                    "type": "border",
                    "layoutType": "block",
                    "text": "边框设置",
                    "bindKey": "Btn2borderDefault"
                },
                {
                    "type": "colorPicker",
                    "layoutType": "inline",
                    "text": "背景色",
                    "bindKey": "Btn2bgColorDefault",
                    "placeholder": "请选择颜色",
                    "default": {}
                },
                {
                    "type": "uploadImage",
                    "layoutType": "inline",
                    "text": "背景图片",
                    "bindKey": "Btn2bgImgUrlDefault",
                    "placeholder": "可输入图片地址或直接上传"
                },
                {
                    "type": "inputNumberUnit",
                    "layoutType": "inline",
                    "text": "横向偏移",
                    "bindKey": "Btn2positionXDefault",
                    "dictionary": [
                        {
                            "label": "px",
                            "value": "px"
                        },
                        {
                            "label": "%",
                            "value": "%"
                        },
                        {
                            "label": "em",
                            "value": "em"
                        }
                    ],
                    "display": "@[Btn2bgImgUrlDefault]"
                },
                {
                    "type": "inputNumberUnit",
                    "layoutType": "inline",
                    "text": "纵向偏移",
                    "bindKey": "Btn2positionYDefault",
                    "dictionary": [
                        {
                            "label": "px",
                            "value": "px"
                        },
                        {
                            "label": "%",
                            "value": "%"
                        },
                        {
                            "label": "em",
                            "value": "em"
                        }
                    ],
                    "display": "@[Btn2bgImgUrlDefault]"
                },
                {
                    "type": "radio",
                    "layoutType": "block",
                    "text": "背景大小",
                    "bindKey": "Btn2bgSizeDefault",
                    "dictionary": [
                        {
                            "label": "裁切显示",
                            "value": "cover"
                        },
                        {
                            "label": "完全显示",
                            "value": "contain"
                        },
                        {
                            "label": "自定义",
                            "value": "customBtn2"
                        }
                    ],
                    "display": "@[Btn2bgImgUrlDefault]"
                },
                {
                    "type": "inputNumberUnit",
                    "layoutType": "inline",
                    "text": "宽度",
                    "bindKey": "Btn2bgSizeWidthDefault",
                    "dictionary": [
                        {
                            "label": "px",
                            "value": "px"
                        },
                        {
                            "label": "%",
                            "value": "%"
                        },
                        {
                            "label": "em",
                            "value": "em"
                        }
                    ],
                    "display": "@[bgSizeDefault=='customBtn2']"
                },
                {
                    "type": "inputNumberUnit",
                    "layoutType": "inline",
                    "text": "高度",
                    "bindKey": "Btn2bgSizeHeightDefault",
                    "dictionary": [
                        {
                            "label": "px",
                            "value": "px"
                        },
                        {
                            "label": "%",
                            "value": "%"
                        },
                        {
                            "label": "em",
                            "value": "em"
                        }
                    ],
                    "display": "@[bgSizeDefault=='customBtn2']"
                },
                {
                    "type": "radio",
                    "layoutType": "block",
                    "text": "平铺模式",
                    "bindKey": "Btn2bgRepeatDefault",
                    "dictionary": [
                        {
                            "label": "双向重复",
                            "value": "repeat"
                        },
                        {
                            "label": "水平重复",
                            "value": "repeat-x"
                        },
                        {
                            "label": "垂直重复",
                            "value": "repeat-y"
                        },
                        {
                            "label": "不重复",
                            "value": "no-repeat"
                        },
                        {
                            "label": "继承",
                            "value": "inherit"
                        }
                    ],
                    "display": "@[Btn2bgImgUrlDefault]"
                },
                {
                    "type": "radio",
                    "layoutType": "inline",
                    "text": "背景模式",
                    "bindKey": "Btn2bgAttachmentDefault",
                    "dictionary": [
                        {
                            "label": "固定",
                            "value": "fixed"
                        },
                        {
                            "label": "滚动",
                            "value": "scroll"
                        },
                        {
                            "label": "继承",
                            "value": "inherit"
                        }
                    ],
                    "display": "@[Btn2bgImgUrlDefault]"
                }
            ]
        },
        {
            "type": "group",
            "text": "样式设置(hover)",
            "desc": "点击？查看样式设置用法指南",
            "helpUrl": "",
            "display": "@[Btn2buttonType=='customBtn2']",
            "children": [
                {
                    "type": "font",
                    "layoutType": "block",
                    "text": "文字",
                    "bindKey": "Btn2fontHover"
                },
                {
                    "type": "border",
                    "layoutType": "block",
                    "text": "边框设置",
                    "bindKey": "Btn2borderHover"
                },
                {
                    "type": "colorPicker",
                    "layoutType": "inline",
                    "text": "背景色",
                    "bindKey": "Btn2bgColorHover",
                    "placeholder": "请选择颜色",
                    "default": {}
                },
                {
                    "type": "uploadImage",
                    "layoutType": "inline",
                    "text": "背景图片",
                    "bindKey": "Btn2bgImgUrlHover",
                    "placeholder": "可输入图片地址或直接上传"
                },
                {
                    "type": "inputNumberUnit",
                    "layoutType": "inline",
                    "text": "横向偏移",
                    "bindKey": "Btn2positionXHover",
                    "dictionary": [
                        {
                            "label": "px",
                            "value": "px"
                        },
                        {
                            "label": "%",
                            "value": "%"
                        },
                        {
                            "label": "em",
                            "value": "em"
                        }
                    ],
                    "display": "@[bgImgUrlHover]"
                },
                {
                    "type": "inputNumberUnit",
                    "layoutType": "inline",
                    "text": "纵向偏移",
                    "bindKey": "Btn2positionYHover",
                    "dictionary": [
                        {
                            "label": "px",
                            "value": "px"
                        },
                        {
                            "label": "%",
                            "value": "%"
                        },
                        {
                            "label": "em",
                            "value": "em"
                        }
                    ],
                    "display": "@[bgImgUrlHover]"
                },
                {
                    "type": "radio",
                    "layoutType": "block",
                    "text": "背景大小",
                    "bindKey": "Btn2bgSizeHover",
                    "dictionary": [
                        {
                            "label": "裁切显示",
                            "value": "cover"
                        },
                        {
                            "label": "完全显示",
                            "value": "contain"
                        },
                        {
                            "label": "自定义",
                            "value": "customBtn2"
                        }
                    ],
                    "display": "@[bgImgUrlHover]"
                },
                {
                    "type": "inputNumberUnit",
                    "layoutType": "inline",
                    "text": "宽度",
                    "bindKey": "Btn2bgSizeWidthHover",
                    "dictionary": [
                        {
                            "label": "px",
                            "value": "px"
                        },
                        {
                            "label": "%",
                            "value": "%"
                        },
                        {
                            "label": "em",
                            "value": "em"
                        }
                    ],
                    "display": "@[bgSizeHover=='customBtn2']"
                },
                {
                    "type": "inputNumberUnit",
                    "layoutType": "inline",
                    "text": "高度",
                    "bindKey": "Btn2bgSizeHeightHover",
                    "dictionary": [
                        {
                            "label": "px",
                            "value": "px"
                        },
                        {
                            "label": "%",
                            "value": "%"
                        },
                        {
                            "label": "em",
                            "value": "em"
                        }
                    ],
                    "display": "@[bgSizeHover=='customBtn2']"
                },
                {
                    "type": "radio",
                    "layoutType": "block",
                    "text": "平铺模式",
                    "bindKey": "Btn2bgRepeatHover",
                    "dictionary": [
                        {
                            "label": "双向重复",
                            "value": "repeat"
                        },
                        {
                            "label": "水平重复",
                            "value": "repeat-x"
                        },
                        {
                            "label": "垂直重复",
                            "value": "repeat-y"
                        },
                        {
                            "label": "不重复",
                            "value": "no-repeat"
                        },
                        {
                            "label": "继承",
                            "value": "inherit"
                        }
                    ],
                    "display": "@[bgImgUrlHover]"
                },
                {
                    "type": "radio",
                    "layoutType": "inline",
                    "text": "背景模式",
                    "bindKey": "Btn2bgAttachmentHover",
                    "dictionary": [
                        {
                            "label": "固定",
                            "value": "fixed"
                        },
                        {
                            "label": "滚动",
                            "value": "scroll"
                        },
                        {
                            "label": "继承",
                            "value": "inherit"
                        }
                    ],
                    "display": "@[bgImgUrlHover]"
                }
            ]
        },
        {
            "type": "group",
            "text": "样式设置(focus)",
            "desc": "点击？查看样式设置用法指南",
            "helpUrl": "",
            "display": "@[Btn2buttonType=='customBtn2']",
            "children": [
                {
                    "type": "font",
                    "layoutType": "block",
                    "text": "文字",
                    "bindKey": "Btn2fontFocus"
                },
                {
                    "type": "border",
                    "layoutType": "block",
                    "text": "边框设置",
                    "bindKey": "Btn2borderFocus"
                },
                {
                    "type": "colorPicker",
                    "layoutType": "inline",
                    "text": "背景色",
                    "bindKey": "Btn2bgColorFocus",
                    "placeholder": "请选择颜色",
                    "default": {}
                },
                {
                    "type": "uploadImage",
                    "layoutType": "inline",
                    "text": "背景图片",
                    "bindKey": "Btn2bgImgUrlFocus",
                    "placeholder": "可输入图片地址或直接上传"
                },
                {
                    "type": "inputNumberUnit",
                    "layoutType": "inline",
                    "text": "横向偏移",
                    "bindKey": "Btn2positionXFocus",
                    "dictionary": [
                        {
                            "label": "px",
                            "value": "px"
                        },
                        {
                            "label": "%",
                            "value": "%"
                        },
                        {
                            "label": "em",
                            "value": "em"
                        }
                    ],
                    "display": "@[bgImgUrlFocus]"
                },
                {
                    "type": "inputNumberUnit",
                    "layoutType": "inline",
                    "text": "纵向偏移",
                    "bindKey": "Btn2positionYFocus",
                    "dictionary": [
                        {
                            "label": "px",
                            "value": "px"
                        },
                        {
                            "label": "%",
                            "value": "%"
                        },
                        {
                            "label": "em",
                            "value": "em"
                        }
                    ],
                    "display": "@[bgImgUrlFocus]"
                },
                {
                    "type": "radio",
                    "layoutType": "block",
                    "text": "背景大小",
                    "bindKey": "Btn2bgSizeFocus",
                    "dictionary": [
                        {
                            "label": "裁切显示",
                            "value": "cover"
                        },
                        {
                            "label": "完全显示",
                            "value": "contain"
                        },
                        {
                            "label": "自定义",
                            "value": "customBtn2"
                        }
                    ],
                    "display": "@[bgImgUrlFocus]"
                },
                {
                    "type": "inputNumberUnit",
                    "layoutType": "inline",
                    "text": "宽度",
                    "bindKey": "Btn2bgSizeWidthFocus",
                    "dictionary": [
                        {
                            "label": "px",
                            "value": "px"
                        },
                        {
                            "label": "%",
                            "value": "%"
                        },
                        {
                            "label": "em",
                            "value": "em"
                        }
                    ],
                    "display": "@[bgSizeFocus=='customBtn2']"
                },
                {
                    "type": "inputNumberUnit",
                    "layoutType": "inline",
                    "text": "高度",
                    "bindKey": "Btn2bgSizeHeightFocus",
                    "dictionary": [
                        {
                            "label": "px",
                            "value": "px"
                        },
                        {
                            "label": "%",
                            "value": "%"
                        },
                        {
                            "label": "em",
                            "value": "em"
                        }
                    ],
                    "display": "@[bgSizeFocus=='customBtn2']"
                },
                {
                    "type": "radio",
                    "layoutType": "block",
                    "text": "平铺模式",
                    "bindKey": "Btn2bgRepeatFocus",
                    "dictionary": [
                        {
                            "label": "双向重复",
                            "value": "repeat"
                        },
                        {
                            "label": "水平重复",
                            "value": "repeat-x"
                        },
                        {
                            "label": "垂直重复",
                            "value": "repeat-y"
                        },
                        {
                            "label": "不重复",
                            "value": "no-repeat"
                        },
                        {
                            "label": "继承",
                            "value": "inherit"
                        }
                    ],
                    "display": "@[bgImgUrlFocus]"
                },
                {
                    "type": "radio",
                    "layoutType": "inline",
                    "text": "背景模式",
                    "bindKey": "Btn2bgAttachmentFocus",
                    "dictionary": [
                        {
                            "label": "固定",
                            "value": "fixed"
                        },
                        {
                            "label": "滚动",
                            "value": "scroll"
                        },
                        {
                            "label": "继承",
                            "value": "inherit"
                        }
                    ],
                    "display": "@[bgImgUrlFocus]"
                }
            ]
        },
        {
            "type": "group",
            "text": "样式设置(active)",
            "desc": "点击？查看样式设置用法指南",
            "helpUrl": "",
            "display": "@[Btn2buttonType=='customBtn2']",
            "children": [
                {
                    "type": "font",
                    "layoutType": "block",
                    "text": "文字",
                    "bindKey": "Btn2fontActive"
                },
                {
                    "type": "border",
                    "layoutType": "block",
                    "text": "边框设置",
                    "bindKey": "Btn2borderActive"
                },
                {
                    "type": "colorPicker",
                    "layoutType": "inline",
                    "text": "背景色",
                    "bindKey": "Btn2bgColorActive",
                    "placeholder": "请选择颜色",
                    "default": {}
                },
                {
                    "type": "uploadImage",
                    "layoutType": "inline",
                    "text": "背景图片",
                    "bindKey": "Btn2bgImgUrlActive",
                    "placeholder": "可输入图片地址或直接上传"
                },
                {
                    "type": "inputNumberUnit",
                    "layoutType": "inline",
                    "text": "横向偏移",
                    "bindKey": "Btn2positionXActive",
                    "dictionary": [
                        {
                            "label": "px",
                            "value": "px"
                        },
                        {
                            "label": "%",
                            "value": "%"
                        },
                        {
                            "label": "em",
                            "value": "em"
                        }
                    ],
                    "display": "@[bgImgUrlActive]"
                },
                {
                    "type": "inputNumberUnit",
                    "layoutType": "inline",
                    "text": "纵向偏移",
                    "bindKey": "Btn2positionYActive",
                    "dictionary": [
                        {
                            "label": "px",
                            "value": "px"
                        },
                        {
                            "label": "%",
                            "value": "%"
                        },
                        {
                            "label": "em",
                            "value": "em"
                        }
                    ],
                    "display": "@[bgImgUrlActive]"
                },
                {
                    "type": "radio",
                    "layoutType": "block",
                    "text": "背景大小",
                    "bindKey": "Btn2bgSizeActive",
                    "dictionary": [
                        {
                            "label": "裁切显示",
                            "value": "cover"
                        },
                        {
                            "label": "完全显示",
                            "value": "contain"
                        },
                        {
                            "label": "自定义",
                            "value": "customBtn2"
                        }
                    ],
                    "display": "@[bgImgUrlActive]"
                },
                {
                    "type": "inputNumberUnit",
                    "layoutType": "inline",
                    "text": "宽度",
                    "bindKey": "Btn2bgSizeWidthActive",
                    "dictionary": [
                        {
                            "label": "px",
                            "value": "px"
                        },
                        {
                            "label": "%",
                            "value": "%"
                        },
                        {
                            "label": "em",
                            "value": "em"
                        }
                    ],
                    "display": "@[bgSizeActive=='customBtn2']"
                },
                {
                    "type": "inputNumberUnit",
                    "layoutType": "inline",
                    "text": "高度",
                    "bindKey": "Btn2bgSizeHeightActive",
                    "dictionary": [
                        {
                            "label": "px",
                            "value": "px"
                        },
                        {
                            "label": "%",
                            "value": "%"
                        },
                        {
                            "label": "em",
                            "value": "em"
                        }
                    ],
                    "display": "@[bgSizeActive=='customBtn2']"
                },
                {
                    "type": "radio",
                    "layoutType": "block",
                    "text": "平铺模式",
                    "bindKey": "Btn2bgRepeatActive",
                    "dictionary": [
                        {
                            "label": "双向重复",
                            "value": "repeat"
                        },
                        {
                            "label": "水平重复",
                            "value": "repeat-x"
                        },
                        {
                            "label": "垂直重复",
                            "value": "repeat-y"
                        },
                        {
                            "label": "不重复",
                            "value": "no-repeat"
                        },
                        {
                            "label": "继承",
                            "value": "inherit"
                        }
                    ],
                    "display": "@[bgImgUrlActive]"
                },
                {
                    "type": "radio",
                    "layoutType": "inline",
                    "text": "背景模式",
                    "bindKey": "Btn2bgAttachmentActive",
                    "dictionary": [
                        {
                            "label": "固定",
                            "value": "fixed"
                        },
                        {
                            "label": "滚动",
                            "value": "scroll"
                        },
                        {
                            "label": "继承",
                            "value": "inherit"
                        }
                    ],
                    "display": "@[bgImgUrlActive]"
                }
            ]
        },
        {
            "type": "group",
            "text": "高级",
            "desc": "点击？查看高级设置用法指南",
            "children": [
                {
                    "type": "actionSelect",
                    "layoutType": "block",
                    "text": "点击时动作",
                    "bindKey": "Btn2clickFunction",
                    "desc": "点击的时候会调用设置的自定义函数，接收参数为格式为{customBtn2Param:自定义的}",
                    "multiple": true
                },
                {
                    "type": "pageModuleSelect",
                    "layoutType": "block",
                    "text": "点击发送组件消息范围",
                    "desc": "当点击的时候需要联动其他组件结果值的组件范围",
                    "bindKey": "Btn2linkagePageModule",
                    "multiple": true
                },
                {
                    "type": "input",
                    "layoutType": "inline",
                    "text": "消息Key",
                    "bindKey": "Btn2messageKey",
                    "desc": "发送组件消息的messageKey，用于联合匹配其他组件进行判定",
                    "default": "buttonClick"
                }
            ]
        }

    ]
}